hashid_field/__init__.py
hashid_field/admin.py
hashid_field/apps.py
hashid_field/auto_field.py
hashid_field/conf.py
hashid_field/descriptor.py
hashid_field/field.py
hashid_field/hashid.py
hashid_field/lookups.py
hashid_field/py.typed
hashid_field/rest.py
shopcloud_django_hashid-0.7.0.dist-info/licenses/LICENSE
shopcloud_django_hashid-0.7.0.dist-info/METADATA
shopcloud_django_hashid-0.7.0.dist-info/WHEEL
shopcloud_django_hashid-0.7.0.dist-info/top_level.txt
shopcloud_django_hashid-0.7.0.dist-info/RECORD
