Metadata-Version: 2.4
Name: shopcloud-django-hashid
Version: 0.7.0
Summary: A drop-in replacement for django-hashid-field with Django 5.x/6.x support
Author-email: ShopCloud <dev@shopcloud.io>
License: MIT
Project-URL: Homepage, https://github.com/Talk-Point/shopcloud-django-hashid
Project-URL: Documentation, https://github.com/Talk-Point/shopcloud-django-hashid#readme
Project-URL: Repository, https://github.com/Talk-Point/shopcloud-django-hashid.git
Project-URL: Changelog, https://github.com/Talk-Point/shopcloud-django-hashid/blob/master/CHANGELOG.md
Project-URL: Issues, https://github.com/Talk-Point/shopcloud-django-hashid/issues
Keywords: django,hashid,hashids,field,obfuscation
Classifier: Development Status :: 4 - Beta
Classifier: Environment :: Web Environment
Classifier: Framework :: Django
Classifier: Framework :: Django :: 5.0
Classifier: Framework :: Django :: 5.1
Classifier: Framework :: Django :: 5.2
Classifier: Framework :: Django :: 6.0
Classifier: Intended Audience :: Developers
Classifier: License :: OSI Approved :: MIT License
Classifier: Operating System :: OS Independent
Classifier: Programming Language :: Python :: 3
Classifier: Programming Language :: Python :: 3.12
Classifier: Programming Language :: Python :: 3.13
Classifier: Topic :: Internet :: WWW/HTTP
Classifier: Topic :: Software Development :: Libraries :: Python Modules
Requires-Python: >=3.12
License-File: LICENSE
Requires-Dist: Django>=5.0
Requires-Dist: hashids>=1.3.1
Provides-Extra: dev
Requires-Dist: pytest>=7.0; extra == "dev"
Requires-Dist: pytest-django>=4.5; extra == "dev"
Requires-Dist: pytest-cov>=4.0; extra == "dev"
Requires-Dist: tox>=4.0; extra == "dev"
Requires-Dist: ruff>=0.1.0; extra == "dev"
Requires-Dist: mypy>=1.0; extra == "dev"
Requires-Dist: django-stubs>=4.0; extra == "dev"
Provides-Extra: drf
Requires-Dist: djangorestframework>=3.14; extra == "drf"
Dynamic: license-file
